_c_enry.abi3.so
enry-0.1.1.dist-info/METADATA
enry-0.1.1.dist-info/top_level.txt
enry-0.1.1.dist-info/WHEEL
enry-0.1.1.dist-info/RECORD
tests/__init__.py
tests/test_enry.py
enry/definitions.py
enry/__init__.py
enry/types.py
enry/utils.py
