Metadata-Version: 2.1
Name: enry
Version: 0.1.1
Summary: Python bindings for go-enry package
Home-page: UNKNOWN
Author: UNKNOWN
Author-email: UNKNOWN
License: UNKNOWN
Platform: UNKNOWN
Requires-Dist: cffi (>=1.0.0)
